LICENSE
README.md
setup.cfg
setup.py
pyastroweatherio/__init__.py
pyastroweatherio/client.py
pyastroweatherio/const.py
pyastroweatherio/dataclasses.py
pyastroweatherio/errors.py
pyastroweatherio/helper_functions.py
pyastroweatherio.egg-info/PKG-INFO
pyastroweatherio.egg-info/SOURCES.txt
pyastroweatherio.egg-info/dependency_links.txt
pyastroweatherio.egg-info/requires.txt
pyastroweatherio.egg-info/top_level.txt
tests/test_client.py